mediasorter/__init__.py
mediasorter/cli.py
mediasorter/lib/__init__.py
mediasorter/lib/cache.py
mediasorter/lib/config.py
mediasorter/lib/execute.py
mediasorter/lib/metadata.py
mediasorter/lib/models.py
mediasorter/lib/overrides.py
mediasorter/lib/parse.py
mediasorter/lib/sort.py
mediasorter/lib/utils.py
multimediasorter-2.0.3.dist-info/LICENSE
multimediasorter-2.0.3.dist-info/METADATA
multimediasorter-2.0.3.dist-info/WHEEL
multimediasorter-2.0.3.dist-info/entry_points.txt
multimediasorter-2.0.3.dist-info/RECORD
