Metadata-Version: 2.1
Name: multimediasorter
Version: 2.0.3
Summary: 
License: MIT
Requires-Python: >=3.10
Classifier: License :: OSI Approved :: MIT License
Classifier: Programming Language :: Python :: 3
Classifier: Programming Language :: Python :: 3.10
Classifier: Programming Language :: Python :: 3.11
Classifier: Programming Language :: Python :: 3.12
Requires-Dist: PyYAML (>=6.0,<7.0)
Requires-Dist: aiohttp (>=3.8.3,<4.0.0)
Requires-Dist: async-cache (>=1.1.1,<2.0.0)
Requires-Dist: loguru (>=0.7.2,<0.8.0)
Requires-Dist: pydantic (>=1.10.4,<2.0.0)
Requires-Dist: rich (>=13.1.0,<14.0.0)
Requires-Dist: typer (>=0.12.3,<0.13.0)
